anaplan_sdk/__init__.py
anaplan_sdk/_auth.py
anaplan_sdk/_oauth.py
anaplan_sdk/_services.py
anaplan_sdk/_utils.py
anaplan_sdk/exceptions.py
anaplan_sdk/_async_clients/__init__.py
anaplan_sdk/_async_clients/_alm.py
anaplan_sdk/_async_clients/_audit.py
anaplan_sdk/_async_clients/_bulk.py
anaplan_sdk/_async_clients/_cloud_works.py
anaplan_sdk/_async_clients/_cw_flow.py
anaplan_sdk/_async_clients/_scim.py
anaplan_sdk/_async_clients/_transactional.py
anaplan_sdk/_clients/__init__.py
anaplan_sdk/_clients/_alm.py
anaplan_sdk/_clients/_audit.py
anaplan_sdk/_clients/_bulk.py
anaplan_sdk/_clients/_cloud_works.py
anaplan_sdk/_clients/_cw_flow.py
anaplan_sdk/_clients/_scim.py
anaplan_sdk/_clients/_transactional.py
anaplan_sdk/models/__init__.py
anaplan_sdk/models/_alm.py
anaplan_sdk/models/_base.py
anaplan_sdk/models/_bulk.py
anaplan_sdk/models/_task.py
anaplan_sdk/models/_transactional.py
anaplan_sdk/models/cloud_works.py
anaplan_sdk/models/flows.py
anaplan_sdk/models/scim.py
anaplan_sdk-0.5.9.dist-info/METADATA
anaplan_sdk-0.5.9.dist-info/WHEEL
anaplan_sdk-0.5.9.dist-info/licenses/LICENSE
anaplan_sdk-0.5.9.dist-info/RECORD
