Metadata-Version: 2.4
Name: anaplan-sdk
Version: 0.5.9
Summary: Streamlined Python Interface for the Anaplan API.
Project-URL: Homepage, https://vinzenzklass.github.io/anaplan-sdk/
Project-URL: Repository, https://github.com/VinzenzKlass/anaplan-sdk
Project-URL: Documentation, https://vinzenzklass.github.io/anaplan-sdk/
Author-email: Vinzenz Klass <vinzenz.klass@valantic.com>
License-Expression: Apache-2.0
License-File: LICENSE
Keywords: anaplan,anaplan alm api,anaplan api,anaplan audit api,anaplan bulk api,anaplan cloudworks api,anaplan integration,anaplan integration api,anaplan sdk,anaplan transactional api
Classifier: Intended Audience :: Developers
Classifier: Intended Audience :: Information Technology
Classifier: Operating System :: OS Independent
Classifier: Programming Language :: Python
Classifier: Programming Language :: Python :: 3
Classifier: Programming Language :: Python :: 3 :: Only
Classifier: Programming Language :: Python :: 3.10
Classifier: Programming Language :: Python :: 3.11
Classifier: Programming Language :: Python :: 3.12
Classifier: Programming Language :: Python :: 3.13
Classifier: Programming Language :: Python :: 3.14
Requires-Python: >=3.10.4
Requires-Dist: httpx<1.0.0,>=0.27.0
Requires-Dist: pydantic<3.0.0,>=2.7.2
Provides-Extra: cert
Requires-Dist: cryptography<47.0.0,>=42.0.7; extra == 'cert'
Provides-Extra: keyring
Requires-Dist: keyring<26.0.0,>=25.6.0; extra == 'keyring'
Provides-Extra: oauth
Requires-Dist: oauthlib<4.0.0,>=3.0.0; extra == 'oauth'
